justsimplepython/SimpleMath.py
justsimplepython/__init__.py
justsimplepython/basicsetup.py
justsimplepython/launch.py
justsimplepy-2025.0.0.1.1.dist-info/METADATA
justsimplepy-2025.0.0.1.1.dist-info/WHEEL
justsimplepy-2025.0.0.1.1.dist-info/top_level.txt
justsimplepy-2025.0.0.1.1.dist-info/RECORD
